jai/__init__.py
jai/core/__init__.py
jai/core/authentication.py
jai/core/base.py
jai/core/decorators.py
jai/core/exceptions.py
jai/core/jai.py
jai/core/utils_funcs.py
jai/core/validations.py
jai/task/__init__.py
jai/task/base.py
jai/task/explorer.py
jai/task/linear.py
jai/task/query.py
jai/task/trainer.py
jai/task/vectors.py
jai/types/__init__.py
jai/types/generic.py
jai/types/hyperparams.py
jai/types/linear.py
jai/types/responses.py
jai/utilities/__init__.py
jai/utilities/_utils.py
jai/utilities/image.py
jai/utilities/processing.py
jai/utilities/splits.py
jai_sdk-0.25.0.dist-info/LICENSE
jai_sdk-0.25.0.dist-info/METADATA
jai_sdk-0.25.0.dist-info/WHEEL
jai_sdk-0.25.0.dist-info/top_level.txt
jai_sdk-0.25.0.dist-info/RECORD
