Metadata-Version: 2.1
Name: jai-sdk
Version: 0.25.0
Summary: JAI - Trust your data
Home-page: https://github.com/jquant/jai-sdk
Author: JQuant
Author-email: jedis@jquant.com.br
License: MIT
Platform: UNKNOWN
Classifier: License :: OSI Approved :: MIT License
Classifier: Programming Language :: Python :: 3
Classifier: Programming Language :: Python :: 3.9
Classifier: Programming Language :: Python :: 3.10
Classifier: Programming Language :: Python :: 3.11
Requires-Python: >=3.9
Requires-Dist: numpy >=1.21.0
Requires-Dist: pandas >=1.3.0
Requires-Dist: tqdm >=4.61.2
Requires-Dist: pillow >=8.3.2
Requires-Dist: psutil >=5.9.0
Requires-Dist: pydantic >=2.0.0
Requires-Dist: python-decouple >=3.6
Requires-Dist: matplotlib >=3.4.2
Requires-Dist: requests
Requires-Dist: scikit-learn >=0.24.2
